Workbook

Sheet Léeme
A1: Modelo de tu estudio de pilates a 12 meses
A3: Qué hace: con los números de tu estudio, te dice mes a mes cuánto ingresas, cuánto gastas, cuánto te queda y a partir de qué ocupación cubres costes y tu propio sueldo. Es la cuenta de la guía «¿Es rentable un estudio de pilates?» llevada a un año.
A4: Cómo se usa: 1) En la hoja «Supuestos» cambia las celdas crema por tus números. 2) Mira «12 meses» para ver el año. 3) Mira «Equilibrio» para saber la ocupación que necesitas. Prueba a subir el precio o a quitar una clase y vuelve a mirar.
A5: La fórmula de ingresos: plazas por clase × clases a la semana × 4,33 × ocupación × precio medio por plaza sin IVA. 4,33 son las semanas de un mes medio (52 ÷ 12).
A6: Los números que trae son un EJEMPLO para ver cómo funciona, no una recomendación ni la media del sector. Sustitúyelos por los tuyos.
A7: Todos los importes van SIN IVA. Si tus precios publicados llevan IVA, divídelos entre 1,21 antes de ponerlos (el IVA de una clase en un estudio privado es el 21 %).
A8: No es asesoramiento fiscal ni financiero: para impuestos, amortizaciones o una financiación, consúltalo con tu asesoría.
A10: Cómo leer los colores
A11: Celda crema con letra azul: la rellenas tú con tus números.
A12: Celda gris: es una fórmula. No escribas encima: si lo haces, borras la fórmula y la hoja deja de cuadrar.

Sheet Supuestos
A1: Supuestos: tus números
A3: Concepto | B3: Tu valor | C3: Qué poner
A4: Plazas por clase (aforo) | B4: 8 | C4: Las camas o plazas de una clase. Si varía, pon la media.
A5: Clases a la semana | B5: 30 | C5: Todas las clases que das en la semana, de todos los tipos.
A6: Ocupación del primer mes | B6: 0.45 | C6: Qué parte de las plazas se llena el primer mes (0,45 = 45 %).
A7: Cuánto sube la ocupación cada mes (puntos) | B7: 0.03 | C7: Puntos de ocupación que ganas cada mes (0,03 = 3 puntos).
A8: Ocupación máxima que esperas | B8: 0.8 | C8: El techo realista de tu estudio. Más de 85 % cuesta sostenerlo.
A9: Precio medio por plaza, SIN IVA (€) | B9: 17 | C9: Lo que ingresas de media por una plaza ocupada, quitado el IVA.
A10: Comisión de cobro (%) | B10: 0.015 | C10: Lo que se come el cobro con tarjeta o domiciliación (pon 0 si no hay).
A11: Coste de la instructora por clase (€) | B11: 22 | C11: Lo que te cuesta una clase en instructora, con su Seguridad Social.
A12: Alquiler del local al mes (€) | B12: 1800 | C12: Sin IVA.
A13: Suministros y gastos generales al mes (€) | B13: 350 | C13: Luz, agua, limpieza, internet…
A14: Software, seguros y asesoría al mes (€) | B14: 300 | C14: Programa de reservas, seguro de responsabilidad, gestoría.
A15: Marketing al mes (€) | B15: 250 | C15: Anuncios, redes, material.
... A20: Semanas de un mes medio (fijo) | B20: 4.33 | C20: 52 ÷ 12 = 4,33. No lo cambies.

Sheet 12 meses
A1: Tu año, mes a mes (todo sin IVA)
A3: Concepto | B3: Mes 1 | C3: Mes 2 | D3: Mes 3 | E3: Mes 4 | F3: Mes 5 | G3: Mes 6 | H3: Mes 7 | I3: Mes 8 | J3: Mes 9 | K3: Mes 10 | L3: Mes 11 | M3: Mes 12 | N3: Total año
A4: Mes | B4: 1 | C4: 2 | D4: 3 | E4: 4 | F4: 5 | G4: 6 | H4: 7 | I4: 8 | J4: 9 | K4: 10 | L4: 11 | M4: 12
A5: Ocupación | B5: =MIN(Supuestos!$B$8,Supuestos!$B$6+(B4-1)*Supuestos!$B$7) | C5: =MIN(Supuestos!$B$8,Supuestos!$B$6+(C4-1)*Supuestos!$B$7) | D5: =MIN(Supuestos!$B$8,Supuestos!$B$6+(D4-1)*Supuestos!$B$7) | E5: =MIN(Supuestos!$B$8,Supuestos!$B$6+(E4-1)*Supuestos!$B$7) | F5: =MIN(Supuestos!$B$8,Supuestos!$B$6+(F4-1)*Supuestos!$B$7) | G5: =MIN(Supuestos!$B$8,Supuestos!$B$6+(G4-1)*Supuestos!$B$7) | H5: =MIN(Supuestos!$B$8,Supuestos!$B$6+(H4-1)*Supuestos!$B$7) | I5: =MIN(Supuestos!$B$8,Supuestos!$B$6+(I4-1)*Supuestos!$B$7) | ... M5: =MIN(Supuestos!$B$8,Supuestos!$B$6+(M4-1)*Supuestos!$B$7)
A6: Plazas ofrecidas | B6: =Supuestos!$B$4*Supuestos!$B$5*Supuestos!$B$20 | C6: =Supuestos!$B$4*Supuestos!$B$5*Supuestos!$B$20 | D6: =Supuestos!$B$4*Supuestos!$B$5*Supuestos!$B$20 | E6: =Supuestos!$B$4*Supuestos!$B$5*Supuestos!$B$20 | F6: =Supuestos!$B$4*Supuestos!$B$5*Supuestos!$B$20 | G6: =Supuestos!$B$4*Supuestos!$B$5*Supuestos!$B$20 | H6: =Supuestos!$B$4*Supuestos!$B$5*Supuestos!$B$20 | I6: =Supuestos!$B$4*Supuestos!$B$5*Supuestos!$B$20 | ... M6: =Supuestos!$B$4*Supuestos!$B$5*Supuestos!$B$20 | N6: =SUM(B6:M6)
A7: Plazas ocupadas | B7: =B6*B5 | C7: =C6*C5 | D7: =D6*D5 | E7: =E6*E5 | F7: =F6*F5 | G7: =G6*G5 | H7: =H6*H5 | I7: =I6*I5 | ... M7: =M6*M5 | N7: =SUM(B7:M7)
A8: Ingresos | B8: =B7*Supuestos!$B$9 | C8: =C7*Supuestos!$B$9 | D8: =D7*Supuestos!$B$9 | E8: =E7*Supuestos!$B$9 | F8: =F7*Supuestos!$B$9 | G8: =G7*Supuestos!$B$9 | H8: =H7*Supuestos!$B$9 | I8: =I7*Supuestos!$B$9 | ... M8: =M7*Supuestos!$B$9 | N8: =SUM(B8:M8)
A9: Comisiones de cobro | B9: =B8*Supuestos!$B$10 | C9: =C8*Supuestos!$B$10 | D9: =D8*Supuestos!$B$10 | E9: =E8*Supuestos!$B$10 | F9: =F8*Supuestos!$B$10 | G9: =G8*Supuestos!$B$10 | H9: =H8*Supuestos!$B$10 | I9: =I8*Supuestos!$B$10 | ... M9: =M8*Supuestos!$B$10 | N9: =SUM(B9:M9)
A10: Instructoras | B10: =Supuestos!$B$11*Supuestos!$B$5*Supuestos!$B$20 | C10: =Supuestos!$B$11*Supuestos!$B$5*Supuestos!$B$20 | D10: =Supuestos!$B$11*Supuestos!$B$5*Supuestos!$B$20 | E10: =Supuestos!$B$11*Supuestos!$B$5*Supuestos!$B$20 | F10: =Supuestos!$B$11*Supuestos!$B$5*Supuestos!$B$20 | G10: =Supuestos!$B$11*Supuestos!$B$5*Supuestos!$B$20 | H10: =Supuestos!$B$11*Supuestos!$B$5*Supuestos!$B$20 | I10: =Supuestos!$B$11*Supuestos!$B$5*Supuestos!$B$20 | ... M10: =Supuestos!$B$11*Supuestos!$B$5*Supuestos!$B$20 | N10: =SUM(B10:M10)
A11: Costes fijos (local, gastos, software, marketing, reserva) | B11: =Supuestos!$B$12+Supuestos!$B$13+Supuestos!$B$14+Supuestos!$B$15+Supuestos!$B$16 | C11: =Supuestos!$B$12+Supuestos!$B$13+Supuestos!$B$14+Supuestos!$B$15+Supuestos!$B$16 | D11: =Supuestos!$B$12+Supuestos!$B$13+Supuestos!$B$14+Supuestos!$B$15+Supuestos!$B$16 | E11: =Supuestos!$B$12+Supuestos!$B$13+Supuestos!$B$14+Supuestos!$B$15+Supuestos!$B$16 | F11: =Supuestos!$B$12+Supuestos!$B$13+Supuestos!$B$14+Supuestos!$B$15+Supuestos!$B$16 | G11: =Supuestos!$B$12+Supuestos!$B$13+Supuestos!$B$14+Supuestos!$B$15+Supuestos!$B$16 | H11: =Supuestos!$B$12+Supuestos!$B$13+Supuestos!$B$14+Supuestos!$B$15+Supuestos!$B$16 | I11: =Supuestos!$B$12+Supuestos!$B$13+Supuestos!$B$14+Supuestos!$B$15+Supuestos!$B$16 | ... M11: =Supuestos!$B$12+Supuestos!$B$13+Supuestos!$B$14+Supuestos!$B$15+Supuestos!$B$16 | N11: =SUM(B11:M11)
A12: Resultado antes de ti | B12: =B8-B9-B10-B11 | C12: =C8-C9-C10-C11 | D12: =D8-D9-D10-D11 | E12: =E8-E9-E10-E11 | F12: =F8-F9-F10-F11 | G12: =G8-G9-G10-G11 | H12: =H8-H9-H10-H11 | I12: =I8-I9-I10-I11 | ... M12: =M8-M9-M10-M11 | N12: =SUM(B12:M12)
A13: Tu sueldo objetivo | B13: =Supuestos!$B$17 | C13: =Supuestos!$B$17 | D13: =Supuestos!$B$17 | E13: =Supuestos!$B$17 | F13: =Supuestos!$B$17 | G13: =Supuestos!$B$17 | H13: =Supuestos!$B$17 | I13: =Supuestos!$B$17 | ... M13: =Supuestos!$B$17 | N13: =SUM(B13:M13)
A14: Resultado después de tu sueldo | B14: =B12-B13 | C14: =C12-C13 | D14: =D12-D13 | E14: =E12-E13 | F14: =F12-F13 | G14: =G12-G13 | H14: =H12-H13 | I14: =I12-I13 | ... M14: =M12-M13 | N14: =SUM(B14:M14)
A15: Acumulado antes de ti | B15: =B12 | C15: =B15+C12 | D15: =C15+D12 | E15: =D15+E12 | F15: =E15+F12 | G15: =F15+G12 | H15: =G15+H12 | I15: =H15+I12 | J15: =I15+J12 | ... M15: =L15+M12
A16: Acumulado después de tu sueldo | B16: =B14 | C16: =B16+C14 | D16: =C16+D14 | E16: =D16+E14 | F16: =E16+F14 | G16: =F16+G14 | H16: =G16+H14 | I16: =H16+I14 | J16: =I16+J14 | ... M16: =L16+M14
A17: ¿Cubre costes? | B17: =IF(B12>=0,"Sí","No") | C17: =IF(C12>=0,"Sí","No") | D17: =IF(D12>=0,"Sí","No") | E17: =IF(E12>=0,"Sí","No") | F17: =IF(F12>=0,"Sí","No") | G17: =IF(G12>=0,"Sí","No") | H17: =IF(H12>=0,"Sí","No") | I17: =IF(I12>=0,"Sí","No") | ... M17: =IF(M12>=0,"Sí","No")
A18: ¿Cubre costes y tu sueldo? | B18: =IF(B14>=0,"Sí","No") | C18: =IF(C14>=0,"Sí","No") | D18: =IF(D14>=0,"Sí","No") | E18: =IF(E14>=0,"Sí","No") | F18: =IF(F14>=0,"Sí","No") | G18: =IF(G14>=0,"Sí","No") | H18: =IF(H14>=0,"Sí","No") | I18: =IF(I14>=0,"Sí","No") | ... M18: =IF(M14>=0,"Sí","No")
A19: Inversión recuperada (1 = sí) | B19: =IF(B16>=Supuestos!$B$18,1,0) | C19: =IF(C16>=Supuestos!$B$18,1,0) | D19: =IF(D16>=Supuestos!$B$18,1,0) | E19: =IF(E16>=Supuestos!$B$18,1,0) | F19: =IF(F16>=Supuestos!$B$18,1,0) | G19: =IF(G16>=Supuestos!$B$18,1,0) | H19: =IF(H16>=Supuestos!$B$18,1,0) | I19: =IF(I16>=Supuestos!$B$18,1,0) | ... M19: =IF(M16>=Supuestos!$B$18,1,0)

Sheet Equilibrio
A1: ¿Qué ocupación necesitas?
A3: Cuenta | B3: Resultado | C3: Cómo se calcula
A4: Plazas ofrecidas al mes | B4: =Supuestos!$B$4*Supuestos!$B$5*Supuestos!$B$20 | C4: Plazas por clase × clases a la semana × 4,33.
A5: Lo que deja cada plaza (€) | B5: =Supuestos!$B$9*(1-Supuestos!$B$10) | C5: Precio medio sin IVA menos la comisión de cobro.
A6: Costes del mes sin tu sueldo (€) | B6: =Supuestos!$B$11*Supuestos!$B$5*Supuestos!$B$20+Supuestos!$B$12+Supuestos!$B$13+Supuestos!$B$14+Supuestos!$B$15+Supuestos!$B$16 | C6: Instructoras + local + gastos + software + marketing + reserva.
A7: Ocupación de equilibrio, sin tu sueldo | B7: =IFERROR(B6/(B4*B5),0) | C7: Costes del mes ÷ (plazas del mes × lo que deja cada plaza).
A8: Ocupación de equilibrio, con tu sueldo | B8: =IFERROR((B6+Supuestos!$B$17)/(B4*B5),0) | C8: La misma cuenta sumando a los costes lo que quieres sacar tú. Esta es la que necesitas de verdad.
A9: Personas por clase para cubrir costes | B9: =B7*Supuestos!$B$4 | C9: Ocupación de equilibrio × plazas por clase.
A10: Personas por clase para cubrir costes y tu sueldo | B10: =B8*Supuestos!$B$4 | C10: Ocupación de equilibrio con sueldo × plazas por clase.
A11: ¿Llegas con tu ocupación máxima? | B11: =IF(Supuestos!$B$8>=B8,"Sí","No") | C11: Compara tu techo de ocupación con la ocupación de equilibrio con sueldo.
A12: Precio mínimo por plaza para llegar con tu ocupación máxima (€) | B12: =IFERROR((B6+Supuestos!$B$17)/(B4*Supuestos!$B$8*(1-Supuestos!$B$10)),0) | C12: El precio medio sin IVA que necesitas para cubrir todo si llenas hasta tu techo.
A13: Mes en que recuperas la inversión | B13: =IFERROR(INDEX('12 meses'!B4:M4,MATCH(1,'12 meses'!B19:M19,0)),"No en 12 meses") | C13: Primer mes con el acumulado después de tu sueldo por encima de la inversión inicial.
