Workbook

Sheet Léeme
A1: Simulador de tu escalera de precios de bonos y cuotas
A3: Qué hace: parte del precio de tu clase suelta y de un descuento por escalón, te dice lo que sale cada sesión y el ahorro de cada producto, y te deja comparar hasta tres escenarios de precios con lo que vendes al mes. Es la escalera de la guía «Bonos de pilates» con tus números.
A4: Cómo se usa: 1) En «Escalera» pon tu clase suelta, tus descuentos y lo que te cuesta una plaza. 2) En «Escenarios» pon cuántos productos vendes al mes y prueba otros precios en las columnas «A» y «B». 3) Mira las alertas en rojo.
A5: Dos errores que avisa: un escalón por debajo de lo que te cuesta una plaza (vendes con pérdida), y un bono de 10 más barato por sesión que la cuota de una clase semanal (empujas a tus alumnas fuera de la cuota).
A6: Los precios llevan IVA (es lo que publican los estudios); el coste por plaza va SIN IVA. Para comparar, el modelo quita el 21 % al precio antes de mirar si cubre el coste.
A7: Los números que trae son un ejemplo (25 € la suelta, bonos al 12 % y al 20 %, cuotas al 24 % y 34 %). Sustitúyelos por los tuyos.
A8: Las cuotas se calculan con cuatro clases al mes (una a la semana) y ocho (dos a la semana). Es una aproximación: un mes real tiene entre 4 y 5 semanas.
A9: No es asesoramiento fiscal ni de precios: es una calculadora. Revisa con tu asesoría cualquier decisión con impacto fiscal.
A11: Cómo leer los colores
A12: Celda crema con letra azul: la rellenas tú con tus números.
A13: Celda gris: es una fórmula. No escribas encima: si lo haces, borras la fórmula y la hoja deja de cuadrar.

Sheet Escalera
A1: Tu escalera de precios
A3: Precio de la clase suelta, con IVA (€) | B3: 25
A4: Lo que te cuesta una plaza ocupada, SIN IVA (€) | B4: 11 | C4: Pon 0 si no quieres que avise del coste. Cómo calcularlo: guía «¿Es rentable un estudio de pilates?».
A5: IVA de una clase (fijo) | B5: 0.21
A7: Producto | B7: Sesiones | C7: Descuento por sesión | D7: Precio por sesión (€) | E7: Precio del producto (€) | F7: Ahorro frente a la suelta | G7: Alerta
A8: Clase suelta | B8: 1 | C8: 0 | D8: =ROUND($B$3*(1-C8),2) | E8: =ROUND(D8*B8,2) | F8: =IF($B$3>0,ROUND((1-D8/$B$3)*100,0)/100,0) | G8: =IF(AND($B$4>0,D8/(1+$B$5)<$B$4),"Por debajo de tu coste","")
A9: Bono de 5 sesiones | B9: 5 | C9: 0.12 | D9: =ROUND($B$3*(1-C9),2) | E9: =ROUND(D9*B9,2) | F9: =IF($B$3>0,ROUND((1-D9/$B$3)*100,0)/100,0) | G9: =IF(AND($B$4>0,D9/(1+$B$5)<$B$4),"Por debajo de tu coste","")
A10: Bono de 10 sesiones | B10: 10 | C10: 0.2 | D10: =ROUND($B$3*(1-C10),2) | E10: =ROUND(D10*B10,2) | F10: =IF($B$3>0,ROUND((1-D10/$B$3)*100,0)/100,0) | G10: =IF(AND($B$4>0,D10/(1+$B$5)<$B$4),"Por debajo de tu coste","")
A11: Cuota de 1 clase a la semana (al mes) | B11: 4 | C11: 0.24 | D11: =ROUND($B$3*(1-C11),2) | E11: =ROUND(D11*B11,2) | F11: =IF($B$3>0,ROUND((1-D11/$B$3)*100,0)/100,0) | G11: =IF(AND($B$4>0,D11/(1+$B$5)<$B$4),"Por debajo de tu coste","")
A12: Cuota de 2 clases a la semana (al mes) | B12: 8 | C12: 0.34 | D12: =ROUND($B$3*(1-C12),2) | E12: =ROUND(D12*B12,2) | F12: =IF($B$3>0,ROUND((1-D12/$B$3)*100,0)/100,0) | G12: =IF(AND($B$4>0,D12/(1+$B$5)<$B$4),"Por debajo de tu coste","")
A14: ¿El bono de 10 sale más barato por sesión que la cuota de 1 clase semanal? | F14: =IF($B$3*(1-C10)<$B$3*(1-C11),"Sí: empuja fuera de la cuota","No")
A16: Las cuotas son el precio al mes; «sesiones» es cuántas clases incluye ese mes (4 y 8).

Sheet Escenarios
A1: Compara tres escenarios con lo que vendes al mes
B3: Ahora | C3: Escenario A | D3: Escenario B
A4: Descuentos por sesión
A5: Bono de 5 sesiones | B5: =Escalera!C9 | C5: 0.1 | D5: 0.15
A6: Bono de 10 sesiones | B6: =Escalera!C10 | C6: 0.18 | D6: 0.22
A7: Cuota de 1 clase a la semana | B7: =Escalera!C11 | C7: 0.24 | D7: 0.26
A8: Cuota de 2 clases a la semana | B8: =Escalera!C12 | C8: 0.34 | D8: 0.36
A9: «Ahora» sale de la hoja «Escalera». En A y B pon los descuentos que quieres probar.
A11: Lo que vendes al mes (unidades)
A12: Clases sueltas | B12: 60 | C12: 60 | D12: 60
A13: Bonos de 5 sesiones | B13: 12 | C13: 12 | D13: 12
A14: Bonos de 10 sesiones | B14: 10 | C14: 10 | D14: 10
A15: Cuotas de 1 clase a la semana | B15: 25 | C15: 25 | D15: 25
A16: Cuotas de 2 clases a la semana | B16: 15 | C16: 15 | D16: 15
A17: Si un escenario cambia lo que vendes (más bonos, menos sueltas…), cámbialo aquí. Cada columna es independiente.
A19: Resultado del mes
A20: Precio por sesión del bono de 5 (€) | B20: =ROUND(Escalera!$B$3*(1-B5),2) | C20: =ROUND(Escalera!$B$3*(1-C5),2) | D20: =ROUND(Escalera!$B$3*(1-D5),2)
A21: Precio por sesión del bono de 10 (€) | B21: =ROUND(Escalera!$B$3*(1-B6),2) | C21: =ROUND(Escalera!$B$3*(1-C6),2) | D21: =ROUND(Escalera!$B$3*(1-D6),2)
A22: Precio por sesión de la cuota de 1 clase (€) | B22: =ROUND(Escalera!$B$3*(1-B7),2) | C22: =ROUND(Escalera!$B$3*(1-C7),2) | D22: =ROUND(Escalera!$B$3*(1-D7),2)
A23: Precio por sesión de la cuota de 2 clases (€) | B23: =ROUND(Escalera!$B$3*(1-B8),2) | C23: =ROUND(Escalera!$B$3*(1-C8),2) | D23: =ROUND(Escalera!$B$3*(1-D8),2)
A24: Ingresos del mes, con IVA (€) | B24: =ROUND(B12*Escalera!$B$3+B13*B20*5+B14*B21*10+B15*B22*4+B16*B23*8,2) | C24: =ROUND(C12*Escalera!$B$3+C13*C20*5+C14*C21*10+C15*C22*4+C16*C23*8,2) | D24: =ROUND(D12*Escalera!$B$3+D13*D20*5+D14*D21*10+D15*D22*4+D16*D23*8,2)
A25: Ingresos del mes, sin IVA (€) | B25: =ROUND(B24/(1+Escalera!$B$5),2) | C25: =ROUND(C24/(1+Escalera!$B$5),2) | D25: =ROUND(D24/(1+Escalera!$B$5),2)
A26: Sesiones vendidas en el mes | B26: =B12+B13*5+B14*10+B15*4+B16*8 | C26: =C12+C13*5+C14*10+C15*4+C16*8 | D26: =D12+D13*5+D14*10+D15*4+D16*8
A27: Coste de esas plazas (€) | B27: =ROUND(B26*Escalera!$B$4,2) | C27: =ROUND(C26*Escalera!$B$4,2) | D27: =ROUND(D26*Escalera!$B$4,2)
A28: Margen del mes sobre el coste de la plaza (€) | B28: =ROUND(B25-B27,2) | C28: =ROUND(C25-C27,2) | D28: =ROUND(D25-D27,2)
A29: Ingreso medio por sesión, sin IVA (€) | B29: =IF(B26>0,ROUND(B25/B26,2),0) | C29: =IF(C26>0,ROUND(C25/C26,2),0) | D29: =IF(D26>0,ROUND(D25/D26,2),0)
A30: Diferencia de margen frente a «Ahora» (€) | B30: =ROUND(B28-$B$28,2) | C30: =ROUND(C28-$B$28,2) | D30: =ROUND(D28-$B$28,2)
A31: Alerta: algún escalón por debajo de tu coste | B31: =IF(AND(Escalera!$B$4>0,MIN(Escalera!$D$8,B20,B21,B22,B23)/(1+Escalera!$B$5)<Escalera!$B$4),"Sí","No") | C31: =IF(AND(Escalera!$B$4>0,MIN(Escalera!$D$8,C20,C21,C22,C23)/(1+Escalera!$B$5)<Escalera!$B$4),"Sí","No") | D31: =IF(AND(Escalera!$B$4>0,MIN(Escalera!$D$8,D20,D21,D22,D23)/(1+Escalera!$B$5)<Escalera!$B$4),"Sí","No")
A32: Alerta: el bono de 10 canibaliza la cuota | B32: =IF(B21<B22,"Sí","No") | C32: =IF(C21<C22,"Sí","No") | D32: =IF(D21<D22,"Sí","No")
A33: El margen es una aproximación: supone que cada sesión vendida se da en el mes y mide solo el coste de la plaza, no el resto de tus gastos fijos.
